saliencytools/__init__.py
saliencytools/maskcompare.py
saliencytools-0.34.dist-info/licenses/LICENSE
test/__init__.py
test/test_metrics.py
test/test_readme.py
saliencytools-0.34.dist-info/METADATA
saliencytools-0.34.dist-info/WHEEL
saliencytools-0.34.dist-info/top_level.txt
saliencytools-0.34.dist-info/RECORD
