Metadata-Version: 2.4
Name: saliencytools
Version: 0.34
Summary: A collection of metrics for comparing saliency maps
Home-page: https://github.com/valevalerio/saliencytools
Author: Valerio Bonsignori
Author-email: Valerio Bonsignori <valerio.bonsignori@phd.unipi.it>
License-Expression: MIT
Project-URL: Homepage, https://github.com/valevalerio/saliencytools
Project-URL: Issues, https://github.com/valevalerio/saliencytools/issues
Project-URL: Documentation, https://valevalerio.github.io/saliencytools/
Classifier: Programming Language :: Python :: 3
Classifier: Operating System :: OS Independent
Requires-Python: >=3.10
License-File: LICENSE
Dynamic: author
Dynamic: home-page
Dynamic: license-file
Dynamic: requires-python
